Workbook

Sheet Instruments
A1: Direct-script instruments for discount-curve interpolation
A3: instrument | B3: definition | C3: handle | D3: market_quote | E3: observation
A4: ptirds-1 | B4: =Instruments!$AA$21 | C4: =Instruments!$AA$22 | D4: =Instruments!$AA$23 | E4: =Instruments!$AA$24
A5: ptirds-2 | B5: =Instruments!$AA$36 | C5: =Instruments!$AA$37 | D5: =Instruments!$AA$38 | E5: =Instruments!$AA$39
A6: ptirds-3 | B6: =Instruments!$AA$51 | C6: =Instruments!$AA$52 | D6: =Instruments!$AA$53 | E6: =Instruments!$AA$54
A7: ptirds-4 | B7: =Instruments!$AA$66 | C7: =Instruments!$AA$67 | D7: =Instruments!$AA$68 | E7: =Instruments!$AA$69
A8: ptirds-5 | B8: =Instruments!$AA$81 | C8: =Instruments!$AA$82 | D8: =Instruments!$AA$83 | E8: =Instruments!$AA$84
A9: ptirds-6 | B9: =Instruments!$AA$96 | C9: =Instruments!$AA$97 | D9: =Instruments!$AA$98 | E9: =Instruments!$AA$99
A10: ptirds-7 | B10: =Instruments!$AA$111 | C10: =Instruments!$AA$112 | D10: =Instruments!$AA$113 | E10: =Instruments!$AA$114
A11: ptirds-8 | B11: =Instruments!$AA$126 | C11: =Instruments!$AA$127 | D11: =Instruments!$AA$128 | E11: =Instruments!$AA$129
A12: ptirds-9 | B12: =Instruments!$AA$141 | C12: =Instruments!$AA$142 | D12: =Instruments!$AA$143 | E12: =Instruments!$AA$144
A13: ptirds-10 | B13: =Instruments!$AA$156 | C13: =Instruments!$AA$157 | D13: =Instruments!$AA$158 | E13: =Instruments!$AA$159
A14: ptirds-11 | B14: =Instruments!$AA$171 | C14: =Instruments!$AA$172 | D14: =Instruments!$AA$173 | E14: =Instruments!$AA$174
A15: ptirds-12 | B15: =Instruments!$AA$188 | C15: =Instruments!$AA$189 | D15: =Instruments!$AA$190 | E15: =Instruments!$AA$191
A16: ptirds-13 | B16: =Instruments!$AA$209 | C16: =Instruments!$AA$210 | D16: =Instruments!$AA$211 | E16: =Instruments!$AA$212
A20: ptirds-1 script definition
A21: kind | B21: key | C21: text | E21: field | F21: value | H21: key | I21: type | J21: unit | K21: role | L21: bindable | M21: lower | N21: upper | O21: lower_inclusive | P21: upper_inclusive | S21: id | T21: kind | U21: receiver | V21: parameter | W21: unit | X21: annuity_sign | Y21: min_abs_annuity | Z21: Definition | AA21: =SCRIPTINSTRUMENTDEFINITION.NEW($A$21:$C$25,$E$21:$F$31,$H$21:$P$23,$S$21:$Y$23,)
A22: Definition | B22: N | C22: 100 | E22: pay_currency | F22: USD | H22: N | I22: Real | J22: Price:USD | K22: Notional | L22: TRUE | M22: 0 | O22: FALSE | P22: TRUE | S22: Price | T22: Price | U22: PAY | W22: Price:USD | Z22: Instrument | AA22: =SCRIPTCALIBRATIONINSTRUMENT.NEW("ptirds-1",AA21,,DATE(2022,1,3))
A23: Definition | B23: K | C23: 0.01 | E23: result_currency | F23: USD | H23: K | I23: Real | J23: Rate | K23: Coupon | L23: TRUE | O23: TRUE | P23: TRUE | S23: ParRate | T23: ParAffineRate | U23: PAY | V23: K | W23: Rate | X23: 1 | Y23: 1e-12 | Z23: Quote | AA23: =CALIBRATIONMARKETQUOTE.NEW("ptirds-1-quote",0.01,"Rate",)
A24: Event | B24: 2022-01-03 | C24: PAY PAYS N*(0.005479452054794521*K) | E24: collateral_currency | F24: USD | Z24: Observation | AA24: =CALIBRATIONOBSERVATION.NEW("ptirds-1-observation",AA22,"ParRate",AA23,1E-10)
A25: Event | B25: 2022-01-03 | C25: PAY PAYS N*(-0.005479452054794521*((1/FIX(IR[USD,DF,2022-01-03,2022-01-01],2022-01-01)-1)/0.005479452054794521)) | E25: collateral_type | F25: OIS
E26: receiver | F26: PAY
E27: notional_parameter | F27: N
E28: settlement | F28: AtEvent
E29: valuation_cashflows | F29: IncludeUnsettledAtValuation
E30: discount_route | F30: USD.OIS
E31: convention_set | F31: dal.fixed-dates/1
A35: ptirds-2 script definition
A36: kind | B36: key | C36: text | E36: field | F36: value | H36: key | I36: type | J36: unit | K36: role | L36: bindable | M36: lower | N36: upper | O36: lower_inclusive | P36: upper_inclusive | S36: id | T36: kind | U36: receiver | V36: parameter | W36: unit | X36: annuity_sign | Y36: min_abs_annuity | Z36: Definition | AA36: =SCRIPTINSTRUMENTDEFINITION.NEW($A$36:$C$40,$E$36:$F$46,$H$36:$P$38,$S$36:$Y$38,)
A37: Definition | B37: N | C37: 100 | E37: pay_currency | F37: USD | H37: N | I37: Real | J37: Price:USD | K37: Notional | L37: TRUE | M37: 0 | O37: FALSE | P37: TRUE | S37: Price | T37: Price | U37: PAY | W37: Price:USD | Z37: Instrument | AA37: =SCRIPTCALIBRATIONINSTRUMENT.NEW("ptirds-2",AA36,,DATE(2022,6,15))
A38: Definition | B38: K | C38: 0.0105 | E38: result_currency | F38: USD | H38: K | I38: Real | J38: Rate | K38: Coupon | L38: TRUE | O38: TRUE | P38: TRUE | S38: ParRate | T38: ParAffineRate | U38: PAY | V38: K | W38: Rate | X38: 1 | Y38: 1e-12 | Z38: Quote | AA38: =CALIBRATIONMARKETQUOTE.NEW("ptirds-2-quote",0.0105,"Rate",)
A39: Event | B39: 2022-06-15 | C39: PAY PAYS N*(0.25205479452054796*K) | E39: collateral_currency | F39: USD | Z39: Observation | AA39: =CALIBRATIONOBSERVATION.NEW("ptirds-2-observation",AA37,"ParRate",AA38,1E-10)
A40: Event | B40: 2022-06-15 | C40: PAY PAYS N*(-0.25205479452054796*((1/FIX(IR[USD,DF,2022-06-15,2022-03-15],2022-03-15)-1)/0.25205479452054796)) | E40: collateral_type | F40: OIS
E41: receiver | F41: PAY
E42: notional_parameter | F42: N
E43: settlement | F43: AtEvent
E44: valuation_cashflows | F44: IncludeUnsettledAtValuation
E45: discount_route | F45: USD.OIS
E46: convention_set | F46: dal.fixed-dates/1
A50: ptirds-3 script definition
A51: kind | B51: key | C51: text | E51: field | F51: value | H51: key | I51: type | J51: unit | K51: role | L51: bindable | M51: lower | N51: upper | O51: lower_inclusive | P51: upper_inclusive | S51: id | T51: kind | U51: receiver | V51: parameter | W51: unit | X51: annuity_sign | Y51: min_abs_annuity | Z51: Definition | AA51: =SCRIPTINSTRUMENTDEFINITION.NEW($A$51:$C$55,$E$51:$F$61,$H$51:$P$53,$S$51:$Y$53,)
A52: Definition | B52: N | C52: 100 | E52: pay_currency | F52: USD | H52: N | I52: Real | J52: Price:USD | K52: Notional | L52: TRUE | M52: 0 | O52: FALSE | P52: TRUE | S52: Price | T52: Price | U52: PAY | W52: Price:USD | Z52: Instrument | AA52: =SCRIPTCALIBRATIONINSTRUMENT.NEW("ptirds-3",AA51,,DATE(2022,9,21))
A53: Definition | B53: K | C53: 0.011200000000000002 | E53: result_currency | F53: USD | H53: K | I53: Real | J53: Rate | K53: Coupon | L53: TRUE | O53: TRUE | P53: TRUE | S53: ParRate | T53: ParAffineRate | U53: PAY | V53: K | W53: Rate | X53: 1 | Y53: 1e-12 | Z53: Quote | AA53: =CALIBRATIONMARKETQUOTE.NEW("ptirds-3-quote",0.011200000000000002,"Rate",)
A54: Event | B54: 2022-09-21 | C54: PAY PAYS N*(0.2684931506849315*K) | E54: collateral_currency | F54: USD | Z54: Observation | AA54: =CALIBRATIONOBSERVATION.NEW("ptirds-3-observation",AA52,"ParRate",AA53,1E-10)
A55: Event | B55: 2022-09-21 | C55: PAY PAYS N*(-0.2684931506849315*((1/FIX(IR[USD,DF,2022-09-21,2022-06-15],2022-06-15)-1)/0.2684931506849315)) | E55: collateral_type | F55: OIS
E56: receiver | F56: PAY
E57: notional_parameter | F57: N
E58: settlement | F58: AtEvent
E59: valuation_cashflows | F59: IncludeUnsettledAtValuation
E60: discount_route | F60: USD.OIS
E61: convention_set | F61: dal.fixed-dates/1
A65: ptirds-4 script definition
A66: kind | B66: key | C66: text | E66: field | F66: value | H66: key | I66: type | J66: unit | K66: role | L66: bindable | M66: lower | N66: upper | O66: lower_inclusive | P66: upper_inclusive | S66: id | T66: kind | U66: receiver | V66: parameter | W66: unit | X66: annuity_sign | Y66: min_abs_annuity | Z66: Definition | AA66: =SCRIPTINSTRUMENTDEFINITION.NEW($A$66:$C$70,$E$66:$F$76,$H$66:$P$68,$S$66:$Y$68,)
A67: Definition | B67: N | C67: 100 | E67: pay_currency | F67: USD | H67: N | I67: Real | J67: Price:USD | K67: Notional | L67: TRUE | M67: 0 | O67: FALSE | P67: TRUE | S67: Price | T67: Price | U67: PAY | W67: Price:USD | Z67: Instrument | AA67: =SCRIPTCALIBRATIONINSTRUMENT.NEW("ptirds-4",AA66,,DATE(2022,12,21))
A68: Definition | B68: K | C68: 0.0116 | E68: result_currency | F68: USD | H68: K | I68: Real | J68: Rate | K68: Coupon | L68: TRUE | O68: TRUE | P68: TRUE | S68: ParRate | T68: ParAffineRate | U68: PAY | V68: K | W68: Rate | X68: 1 | Y68: 1e-12 | Z68: Quote | AA68: =CALIBRATIONMARKETQUOTE.NEW("ptirds-4-quote",0.0116,"Rate",)
A69: Event | B69: 2022-12-21 | C69: PAY PAYS N*(0.2493150684931507*K) | E69: collateral_currency | F69: USD | Z69: Observation | AA69: =CALIBRATIONOBSERVATION.NEW("ptirds-4-observation",AA67,"ParRate",AA68,1E-10)
A70: Event | B70: 2022-12-21 | C70: PAY PAYS N*(-0.2493150684931507*((1/FIX(IR[USD,DF,2022-12-21,2022-09-21],2022-09-21)-1)/0.2493150684931507)) | E70: collateral_type | F70: OIS
E71: receiver | F71: PAY
E72: notional_parameter | F72: N
E73: settlement | F73: AtEvent
E74: valuation_cashflows | F74: IncludeUnsettledAtValuation
E75: discount_route | F75: USD.OIS
E76: convention_set | F76: dal.fixed-dates/1
A80: ptirds-5 script definition
A81: kind | B81: key | C81: text | E81: field | F81: value | H81: key | I81: type | J81: unit | K81: role | L81: bindable | M81: lower | N81: upper | O81: lower_inclusive | P81: upper_inclusive | S81: id | T81: kind | U81: receiver | V81: parameter | W81: unit | X81: annuity_sign | Y81: min_abs_annuity | Z81: Definition | AA81: =SCRIPTINSTRUMENTDEFINITION.NEW($A$81:$C$85,$E$81:$F$91,$H$81:$P$83,$S$81:$Y$83,)
A82: Definition | B82: N | C82: 100 | E82: pay_currency | F82: USD | H82: N | I82: Real | J82: Price:USD | K82: Notional | L82: TRUE | M82: 0 | O82: FALSE | P82: TRUE | S82: Price | T82: Price | U82: PAY | W82: Price:USD | Z82: Instrument | AA82: =SCRIPTCALIBRATIONINSTRUMENT.NEW("ptirds-5",AA81,,DATE(2023,3,15))
A83: Definition | B83: K | C83: 0.0121 | E83: result_currency | F83: USD | H83: K | I83: Real | J83: Rate | K83: Coupon | L83: TRUE | O83: TRUE | P83: TRUE | S83: ParRate | T83: ParAffineRate | U83: PAY | V83: K | W83: Rate | X83: 1 | Y83: 1e-12 | Z83: Quote | AA83: =CALIBRATIONMARKETQUOTE.NEW("ptirds-5-quote",0.0121,"Rate",)
A84: Event | B84: 2023-03-15 | C84: PAY PAYS N*(0.23013698630136986*K) | E84: collateral_currency | F84: USD | Z84: Observation | AA84: =CALIBRATIONOBSERVATION.NEW("ptirds-5-observation",AA82,"ParRate",AA83,1E-10)
A85: Event | B85: 2023-03-15 | C85: PAY PAYS N*(-0.23013698630136986*((1/FIX(IR[USD,DF,2023-03-15,2022-12-21],2022-12-21)-1)/0.23013698630136986)) | E85: collateral_type | F85: OIS
E86: receiver | F86: PAY
E87: notional_parameter | F87: N
E88: settlement | F88: AtEvent
E89: valuation_cashflows | F89: IncludeUnsettledAtValuation
E90: discount_route | F90: USD.OIS
E91: convention_set | F91: dal.fixed-dates/1
A95: ptirds-6 script definition
A96: kind | B96: key | C96: text | E96: field | F96: value | H96: key | I96: type | J96: unit | K96: role | L96: bindable | M96: lower | N96: upper | O96: lower_inclusive | P96: upper_inclusive | S96: id | T96: kind | U96: receiver | V96: parameter | W96: unit | X96: annuity_sign | Y96: min_abs_annuity | Z96: Definition | AA96: =SCRIPTINSTRUMENTDEFINITION.NEW($A$96:$C$100,$E$96:$F$106,$H$96:$P$98,$S$96:$Y$98,)
A97: Definition | B97: N | C97: 100 | E97: pay_currency | F97: USD | H97: N | I97: Real | J97: Price:USD | K97: Notional | L97: TRUE | M97: 0 | O97: FALSE | P97: TRUE | S97: Price | T97: Price | U97: PAY | W97: Price:USD | Z97: Instrument | AA97: =SCRIPTCALIBRATIONINSTRUMENT.NEW("ptirds-6",AA96,,DATE(2023,6,21))
A98: Definition | B98: K | C98: 0.0127 | E98: result_currency | F98: USD | H98: K | I98: Real | J98: Rate | K98: Coupon | L98: TRUE | O98: TRUE | P98: TRUE | S98: ParRate | T98: ParAffineRate | U98: PAY | V98: K | W98: Rate | X98: 1 | Y98: 1e-12 | Z98: Quote | AA98: =CALIBRATIONMARKETQUOTE.NEW("ptirds-6-quote",0.0127,"Rate",)
A99: Event | B99: 2023-06-21 | C99: PAY PAYS N*(0.2684931506849315*K) | E99: collateral_currency | F99: USD | Z99: Observation | AA99: =CALIBRATIONOBSERVATION.NEW("ptirds-6-observation",AA97,"ParRate",AA98,1E-10)
A100: Event | B100: 2023-06-21 | C100: PAY PAYS N*(-0.2684931506849315*((1/FIX(IR[USD,DF,2023-06-21,2023-03-15],2023-03-15)-1)/0.2684931506849315)) | E100: collateral_type | F100: OIS
E101: receiver | F101: PAY
E102: notional_parameter | F102: N
E103: settlement | F103: AtEvent
E104: valuation_cashflows | F104: IncludeUnsettledAtValuation
E105: discount_route | F105: USD.OIS
E106: convention_set | F106: dal.fixed-dates/1
A110: ptirds-7 script definition
A111: kind | B111: key | C111: text | E111: field | F111: value | H111: key | I111: type | J111: unit | K111: role | L111: bindable | M111: lower | N111: upper | O111: lower_inclusive | P111: upper_inclusive | S111: id | T111: kind | U111: receiver | V111: parameter | W111: unit | X111: annuity_sign | Y111: min_abs_annuity | Z111: Definition | AA111: =SCRIPTINSTRUMENTDEFINITION.NEW($A$111:$C$115,$E$111:$F$121,$H$111:$P$113,$S$111:$Y$113,)
A112: Definition | B112: N | C112: 100 | E112: pay_currency | F112: USD | H112: N | I112: Real | J112: Price:USD | K112: Notional | L112: TRUE | M112: 0 | O112: FALSE | P112: TRUE | S112: Price | T112: Price | U112: PAY | W112: Price:USD | Z112: Instrument | AA112: =SCRIPTCALIBRATIONINSTRUMENT.NEW("ptirds-7",AA111,,DATE(2023,9,20))
A113: Definition | B113: K | C113: 0.014499999999999999 | E113: result_currency | F113: USD | H113: K | I113: Real | J113: Rate | K113: Coupon | L113: TRUE | O113: TRUE | P113: TRUE | S113: ParRate | T113: ParAffineRate | U113: PAY | V113: K | W113: Rate | X113: 1 | Y113: 1e-12 | Z113: Quote | AA113: =CALIBRATIONMARKETQUOTE.NEW("ptirds-7-quote",0.014499999999999999,"Rate",)
A114: Event | B114: 2023-09-20 | C114: PAY PAYS N*(0.2493150684931507*K) | E114: collateral_currency | F114: USD | Z114: Observation | AA114: =CALIBRATIONOBSERVATION.NEW("ptirds-7-observation",AA112,"ParRate",AA113,1E-10)
A115: Event | B115: 2023-09-20 | C115: PAY PAYS N*(-0.2493150684931507*((1/FIX(IR[USD,DF,2023-09-20,2023-06-21],2023-06-21)-1)/0.2493150684931507)) | E115: collateral_type | F115: OIS
E116: receiver | F116: PAY
E117: notional_parameter | F117: N
E118: settlement | F118: AtEvent
E119: valuation_cashflows | F119: IncludeUnsettledAtValuation
E120: discount_route | F120: USD.OIS
E121: convention_set | F121: dal.fixed-dates/1
A125: ptirds-8 script definition
...

Sheet LOG_LINEAR
A1: Script yield calibration — LOG_LINEAR
A2: 13 scripted instruments, 14 knots, EXACT solve, AAD Jacobian
A4: Knot dates | B4: =CALIBRATIONDATES.NEW($H$5:$H$18) | D4: field | E4: value | G4: index | H4: knot_date
A5: Geometry | B5: =CURVEINSTRUMENTGEOMETRY.NEW($D$4:$E$14) | D5: today | E5: 44562 | G5: 1 | H5: 44562
A6: Routes | B6: =CURVESCRIPTROUTES.NEW($D$17:$G$18) | D6: currency | E6: USD | G6: 2 | H6: 44635
A7: Market | B7: =CURVEINSTRUMENTMARKET.NEW($D$21:$E$22) | D7: curve_name | E7: ptirds | G7: 3 | H7: 44727
A8: Empty fixings | B8: =MARKETFIXINGSNAPSHOT.NEW(,,) | D8: knot_dates | E8: $B$4 | G8: 4 | H8: 44825
A9: Valuation | B9: =SCRIPTVALUATIONSETTINGS.NEW("ptirds-valuation",$D$25:$E$26,$B$8) | D9: parameterization | E9: LOG_DISCOUNT | G9: 5 | H9: 44916
A10: Solver | B10: =CURVEINSTRUMENTSOLVER.NEW($D$29:$E$35) | D10: knot_policy | E10: INPUT | G10: 6 | H10: 45000
A11: Options | B11: =CURVEINSTRUMENTCALIBRATIONOPTIONS.NEW($D$38:$E$42) | D11: log_df_scheme | E11: LOG_LINEAR | G11: 7 | H11: 45098
A12: Observations | B12: =CALIBRATIONOBSERVATIONS.NEW(Instruments!$E$4:$E$16) | D12: calibrate_discount_curve | E12: TRUE | G12: 8 | H12: 45189
A13: Spec | B13: =CURVEINSTRUMENTCALIBRATIONSPEC.NEW($D$45:$E$50) | D13: target_collateral | E13: OIS | G13: 9 | H13: 45280
A14: Calibration | B14: =CALIBRATE.CURVEINSTRUMENTS($B$13,$B$11) | D14: libor_basis | E14: ACT_365F | G14: 10 | H14: 45366
A15: Status | B15: =CALIBRATIONOUTCOME.GET.STATUS($B$14) | G15: 11 | H15: 45658
A16: Report | B16: =CALIBRATIONOUTCOME.GET.REPORT($B$14) | G16: 12 | H16: 46388
A17: Curve | B17: =CALIBRATIONOUTCOME.GET.CURVE($B$14) | D17: id | E17: projection | F17: collateral | G17: tenor | H17: 47119
D18: USD.OIS | E18: FALSE | F18: OIS | G18: 14 | H18: 48214
D21: field | E21: value
A22: Observation report | D22: routes | E22: $B$6
A23: =CALIBRATIONREPORT.GET.OBSERVATIONS($B$16)
D25: field | E25: value
D26: evaluation_date | E26: 44562
D29: field | E29: value
D30: solve_mode | E30: EXACT
D31: initial_guess | E31: 0.05
D32: smoothing_weight | E32: 1
D33: max_evaluations | E33: 200
D34: max_restarts | E34: 20
D35: fit_norm_tolerance | E35: 1e-08
D38: field | E38: value
D39: evaluation | E39: AutoFast
A40: Fitted parameters | D40: jacobian_mode | E40: AAD
A41: =CALIBRATIONREPORT.GET.PARAMETERS($B$16) | D41: difference_step | E41: 1e-06
D42: compute_quote_jacobian | E42: FALSE
D45: field | E45: value
D46: geometry | E46: $B$5
D47: market | E47: $B$7
D48: valuation | E48: $B$9
D49: observations | E49: $B$12
D50: solver | E50: $B$10

Sheet LOG_CUBIC_NATURAL
A1: Script yield calibration — LOG_CUBIC_NATURAL
A2: 13 scripted instruments, 14 knots, EXACT solve, AAD Jacobian
A4: Knot dates | B4: =CALIBRATIONDATES.NEW($H$5:$H$18) | D4: field | E4: value | G4: index | H4: knot_date
A5: Geometry | B5: =CURVEINSTRUMENTGEOMETRY.NEW($D$4:$E$14) | D5: today | E5: 44562 | G5: 1 | H5: 44562
A6: Routes | B6: =CURVESCRIPTROUTES.NEW($D$17:$G$18) | D6: currency | E6: USD | G6: 2 | H6: 44635
A7: Market | B7: =CURVEINSTRUMENTMARKET.NEW($D$21:$E$22) | D7: curve_name | E7: ptirds | G7: 3 | H7: 44727
A8: Empty fixings | B8: =MARKETFIXINGSNAPSHOT.NEW(,,) | D8: knot_dates | E8: $B$4 | G8: 4 | H8: 44825
A9: Valuation | B9: =SCRIPTVALUATIONSETTINGS.NEW("ptirds-valuation",$D$25:$E$26,$B$8) | D9: parameterization | E9: LOG_DISCOUNT | G9: 5 | H9: 44916
A10: Solver | B10: =CURVEINSTRUMENTSOLVER.NEW($D$29:$E$35) | D10: knot_policy | E10: INPUT | G10: 6 | H10: 45000
A11: Options | B11: =CURVEINSTRUMENTCALIBRATIONOPTIONS.NEW($D$38:$E$42) | D11: log_df_scheme | E11: LOG_CUBIC_NATURAL | G11: 7 | H11: 45098
A12: Observations | B12: =CALIBRATIONOBSERVATIONS.NEW(Instruments!$E$4:$E$16) | D12: calibrate_discount_curve | E12: TRUE | G12: 8 | H12: 45189
A13: Spec | B13: =CURVEINSTRUMENTCALIBRATIONSPEC.NEW($D$45:$E$50) | D13: target_collateral | E13: OIS | G13: 9 | H13: 45280
A14: Calibration | B14: =CALIBRATE.CURVEINSTRUMENTS($B$13,$B$11) | D14: libor_basis | E14: ACT_365F | G14: 10 | H14: 45366
A15: Status | B15: =CALIBRATIONOUTCOME.GET.STATUS($B$14) | G15: 11 | H15: 45658
A16: Report | B16: =CALIBRATIONOUTCOME.GET.REPORT($B$14) | G16: 12 | H16: 46388
A17: Curve | B17: =CALIBRATIONOUTCOME.GET.CURVE($B$14) | D17: id | E17: projection | F17: collateral | G17: tenor | H17: 47119
D18: USD.OIS | E18: FALSE | F18: OIS | G18: 14 | H18: 48214
D21: field | E21: value
A22: Observation report | D22: routes | E22: $B$6
A23: =CALIBRATIONREPORT.GET.OBSERVATIONS($B$16)
D25: field | E25: value
D26: evaluation_date | E26: 44562
D29: field | E29: value
D30: solve_mode | E30: EXACT
D31: initial_guess | E31: 0.05
D32: smoothing_weight | E32: 1
D33: max_evaluations | E33: 200
D34: max_restarts | E34: 20
D35: fit_norm_tolerance | E35: 1e-08
D38: field | E38: value
D39: evaluation | E39: AutoFast
A40: Fitted parameters | D40: jacobian_mode | E40: AAD
A41: =CALIBRATIONREPORT.GET.PARAMETERS($B$16) | D41: difference_step | E41: 1e-06
D42: compute_quote_jacobian | E42: FALSE
D45: field | E45: value
D46: geometry | E46: $B$5
D47: market | E47: $B$7
D48: valuation | E48: $B$9
D49: observations | E49: $B$12
D50: solver | E50: $B$10

Sheet MIXED
A1: Script yield calibration — MIXED
A2: 13 scripted instruments, 14 knots, EXACT solve, AAD Jacobian
A4: Knot dates | B4: =CALIBRATIONDATES.NEW($H$5:$H$18) | D4: field | E4: value | G4: index | H4: knot_date
A5: Geometry | B5: =CURVEINSTRUMENTGEOMETRY.NEW($D$4:$E$14) | D5: today | E5: 44562 | G5: 1 | H5: 44562
A6: Routes | B6: =CURVESCRIPTROUTES.NEW($D$17:$G$18) | D6: currency | E6: USD | G6: 2 | H6: 44635
A7: Market | B7: =CURVEINSTRUMENTMARKET.NEW($D$21:$E$22) | D7: curve_name | E7: ptirds | G7: 3 | H7: 44727
A8: Empty fixings | B8: =MARKETFIXINGSNAPSHOT.NEW(,,) | D8: knot_dates | E8: $B$4 | G8: 4 | H8: 44825
A9: Valuation | B9: =SCRIPTVALUATIONSETTINGS.NEW("ptirds-valuation",$D$25:$E$26,$B$8) | D9: parameterization | E9: LOG_DISCOUNT | G9: 5 | H9: 44916
A10: Solver | B10: =CURVEINSTRUMENTSOLVER.NEW($D$29:$E$35) | D10: knot_policy | E10: INPUT | G10: 6 | H10: 45000
A11: Options | B11: =CURVEINSTRUMENTCALIBRATIONOPTIONS.NEW($D$38:$E$42) | D11: log_df_scheme | E11: MIXED | G11: 7 | H11: 45098
A12: Observations | B12: =CALIBRATIONOBSERVATIONS.NEW(Instruments!$E$4:$E$16) | D12: calibrate_discount_curve | E12: TRUE | G12: 8 | H12: 45189
A13: Spec | B13: =CURVEINSTRUMENTCALIBRATIONSPEC.NEW($D$45:$E$50) | D13: target_collateral | E13: OIS | G13: 9 | H13: 45280
A14: Calibration | B14: =CALIBRATE.CURVEINSTRUMENTS($B$13,$B$11) | D14: libor_basis | E14: ACT_365F | G14: 10 | H14: 45366
A15: Status | B15: =CALIBRATIONOUTCOME.GET.STATUS($B$14) | G15: 11 | H15: 45658
A16: Report | B16: =CALIBRATIONOUTCOME.GET.REPORT($B$14) | G16: 12 | H16: 46388
A17: Curve | B17: =CALIBRATIONOUTCOME.GET.CURVE($B$14) | D17: id | E17: projection | F17: collateral | G17: tenor | H17: 47119
D18: USD.OIS | E18: FALSE | F18: OIS | G18: 14 | H18: 48214
D21: field | E21: value
A22: Observation report | D22: routes | E22: $B$6
A23: =CALIBRATIONREPORT.GET.OBSERVATIONS($B$16)
D25: field | E25: value
D26: evaluation_date | E26: 44562
D29: field | E29: value
D30: solve_mode | E30: EXACT
D31: initial_guess | E31: 0.05
D32: smoothing_weight | E32: 1
D33: max_evaluations | E33: 200
D34: max_restarts | E34: 20
D35: fit_norm_tolerance | E35: 1e-08
D38: field | E38: value
D39: evaluation | E39: AutoFast
A40: Fitted parameters | D40: jacobian_mode | E40: AAD
A41: =CALIBRATIONREPORT.GET.PARAMETERS($B$16) | D41: difference_step | E41: 1e-06
D42: compute_quote_jacobian | E42: FALSE
D45: field | E45: value
D46: geometry | E46: $B$5
D47: market | E47: $B$7
D48: valuation | E48: $B$9
D49: observations | E49: $B$12
D50: solver | E50: $B$10

Sheet Notes
A1: 012.interpolate_curve_script
A3: Initialize DAL | B3: =INIT.GLOBALDATA(1)
A5: The Instruments sheet constructs every definition from dated DAL script source rows. No native swap or native-to-script import function is used.
A6: The three calibration sheets share the same 13 instruments, quotes and 14 knots. Only log_discount_scheme changes: LOG_LINEAR, LOG_CUBIC_NATURAL and MIXED.
A7: ACT/365F accruals are unadjusted; the fixing date is the accrual start. N=100 and each K equals the original instrument's decimal par quote.
A8: The solver uses EXACT, initial guess 0.05, smoothing weight 1, 200 evaluations, 20 restarts and fit_norm_tolerance 1e-8. AAD is selected explicitly.
A9: Run INIT.GLOBALDATA(1), then recalculate the workbook. CALIBRATIONOUTCOME.GET.STATUS should return Succeeded on all three sheets.
A10: Observation and parameter tables are spilled from the typed report. This file contains formulas, not cached results; generating it does not execute Excel.
